MANIFEST.in
README.md
opensearch.py
setup.py
opensearch_python_sdk.egg-info/PKG-INFO
opensearch_python_sdk.egg-info/SOURCES.txt
opensearch_python_sdk.egg-info/dependency_links.txt
opensearch_python_sdk.egg-info/requires.txt
opensearch_python_sdk.egg-info/top_level.txt