Metadata-Version: 1.1
Name: opensearch-python-sdk
Version: 0.0.3
Summary: Python unofficial sdk of aliyun open search
Home-page: https://github.com/bowenpay/opensearch-python-sdk
Author: Kaiyuan Li, Jingping Yi
Author-email: me@defool.me, jingping.yi@gmail.com
License: MIT
Platform: UNKNOWN
Classifier: Topic :: Software Development
Classifier: Development Status :: 5 - Production/Stable
Classifier: Intended Audience :: Developers
Classifier: License :: OSI Approved :: MIT License
Classifier: Programming Language :: Python :: 2.7
Classifier: Programming Language :: Python :: 3.3
Classifier: Programming Language :: Python :: 3.4
